[{"title":"Project Manager","locations":["Tel Aviv","New York","Chiang Mai","London","Bali","Jerusalem","Petah Tikva","Berlin"],"job_type":"freelance","company":"Bcards"},{"title":"DJ","locations":["Tel Aviv","New York","Chiang Mai","London","Bali","Jerusalem","Petah Tikva","Berlin"],"job_type":"project","company":"Bcards"},{"title":"Web designer","locations":["Tel Aviv","New York","Chiang Mai","London","Bali","Jerusalem","Petah Tikva","Berlin"],"job_type":"project","company":"nvideo"},{"title":"Frontend Developer","locations":["Tel Aviv","New York","Chiang Mai","London","Bali","Jerusalem","Petah Tikva","Berlin"],"job_type":"full-time","company":"nvideo"},{"title":"Backend Developer","locations":["Tel Aviv","New York","Chiang Mai","London","Bali","Jerusalem","Petah Tikva","Berlin"],"job_type":"full-time","company":"Eztalk"},{"title":"Film director","locations":["Tel Aviv","New York","Chiang Mai","London","Bali","Jerusalem","Petah Tikva","Berlin"],"job_type":"part-time","company":"backzy"},{"title":"Project Manager","locations":["Tel Aviv","New York","Chiang Mai","London","Bali","Jerusalem","Petah Tikva","Berlin"],"job_type":"full-time","company":"accell"},{"title":"Cabinet maker","locations":["Tel Aviv","New York","Chiang Mai","London","Bali","Jerusalem","Petah Tikva","Berlin"],"job_type":"freelance","company":"locket"},{"title":"Handyman","locations":["Tel Aviv","New York","Chiang Mai","London","Bali","Jerusalem","Petah Tikva","Berlin"],"job_type":"part-time","company":"Dataps"},{"title":"Sculptor","locations":["Tel Aviv","New York","Chiang Mai","London","Bali","Jerusalem","Petah Tikva","Berlin"],"job_type":"part-time","company":"Bcards"},{"title":"Bodyguard","locations":["Tel Aviv","New York","Chiang Mai","London","Bali","Jerusalem","Petah Tikva","Berlin"],"job_type":"freelance","company":"Jokens"},{"title":"Recepetionist","locations":["Tel Aviv","New York","Chiang Mai","London","Bali","Jerusalem","Petah Tikva","Berlin"],"job_type":"freelance","company":"splier"},{"title":"Film director","locations":["Tel Aviv","New York","Chiang Mai","London","Bali","Jerusalem","Petah Tikva","Berlin"],"job_type":"full-time","company":"Bcards"},{"title":"DJ","locations":["Tel Aviv","New York","Chiang Mai","London","Bali","Jerusalem","Petah Tikva","Berlin"],"job_type":"freelance","company":"splier"},{"title":"Business owner","locations":["Tel Aviv","New York","Chiang Mai","London","Bali","Jerusalem","Petah Tikva","Berlin"],"job_type":"project","company":"yeswap"},{"title":"Cabinet maker","locations":["Tel Aviv","New York","Chiang Mai","London","Bali","Jerusalem","Petah Tikva","Berlin"],"job_type":"freelance","company":"packzy"},{"title":"Sculptor","locations":["Tel Aviv","New York","Chiang Mai","London","Bali","Jerusalem","Petah Tikva","Berlin"],"job_type":"part-time","company":"locket"},{"title":"Project Manager","locations":["Tel Aviv","New York","Chiang Mai","London","Bali","Jerusalem","Petah Tikva","Berlin"],"job_type":"project","company":"Jokens"},{"title":"Frontend Developer","locations":["Tel Aviv","New York","Chiang Mai","London","Bali","Jerusalem","Petah Tikva","Berlin"],"job_type":"freelance","company":"Jokens"},{"title":"UI Expert","locations":["Tel Aviv","New York","Chiang Mai","London","Bali","Jerusalem","Petah Tikva","Berlin"],"job_type":"part-time","company":"Jokens"},{"title":"Clairvoyant","locations":["Tel Aviv","New York","Chiang Mai","London","Bali","Jerusalem","Petah Tikva","Berlin"],"job_type":"project","company":"Trummy"},{"title":"Lifeguard","locations":["Tel Aviv","New York","Chiang Mai","London","Bali","Jerusalem","Petah Tikva","Berlin"],"job_type":"freelance","company":"accell"},{"title":"Sculptor","locations":["Tel Aviv","New York","Chiang Mai","London","Bali","Jerusalem","Petah Tikva","Berlin"],"job_type":"freelance","company":"locket"},{"title":"Sculptor","locations":["Tel Aviv","New York","Chiang Mai","London","Bali","Jerusalem","Petah Tikva","Berlin"],"job_type":"project","company":"Spoker"},{"title":"Shark Tamer","locations":["Tel Aviv","New York","Chiang Mai","London","Bali","Jerusalem","Petah Tikva","Berlin"],"job_type":"project","company":"Eztalk"},{"title":"Product Manager","locations":["Tel Aviv","New York","Chiang Mai","London","Bali","Jerusalem","Petah Tikva","Berlin"],"job_type":"project","company":"Trummy"},{"title":"Web designer","locations":["Tel Aviv","New York","Chiang Mai","London","Bali","Jerusalem","Petah Tikva","Berlin"],"job_type":"full-time","company":"Locard"},{"title":"Courier","locations":["Tel Aviv","New York","Chiang Mai","London","Bali","Jerusalem","Petah Tikva","Berlin"],"job_type":"part-time","company":"Locard"},{"title":"Leaflet distributor","locations":["Tel Aviv","New York","Chiang Mai","London","Bali","Jerusalem","Petah Tikva","Berlin"],"job_type":"part-time","company":"Bcards"},{"title":"Recepetionist","locations":["Tel Aviv","New York","Chiang Mai","London","Bali","Jerusalem","Petah Tikva","Berlin"],"job_type":"project","company":"Jokens"},{"title":"Astrologer","locations":["Tel Aviv","New York","Chiang Mai","London","Bali","Jerusalem","Petah Tikva","Berlin"],"job_type":"part-time","company":"Trummy"},{"title":"Frontend Developer","locations":["Tel Aviv","New York","Chiang Mai","London","Bali","Jerusalem","Petah Tikva","Berlin"],"job_type":"full-time","company":"Eztalk"},{"title":"Soldier","locations":["Tel Aviv","New York","Chiang Mai","London","Bali","Jerusalem","Petah Tikva","Berlin"],"job_type":"project","company":"Trummy"},{"title":"Courier","locations":["Tel Aviv","New York","Chiang Mai","London","Bali","Jerusalem","Petah Tikva","Berlin"],"job_type":"project","company":"Trummy"},{"title":"Clairvoyant","locations":["Tel Aviv","New York","Chiang Mai","London","Bali","Jerusalem","Petah Tikva","Berlin"],"job_type":"full-time","company":"Locard"},{"title":"Electrician","locations":["Tel Aviv","New York","Chiang Mai","London","Bali","Jerusalem","Petah Tikva","Berlin"],"job_type":"freelance","company":"Bcards"},{"title":"Recepetionist","locations":["Tel Aviv","New York","Chiang Mai","London","Bali","Jerusalem","Petah Tikva","Berlin"],"job_type":"full-time","company":"locket"},{"title":"Cabinet maker","locations":["Tel Aviv","New York","Chiang Mai","London","Bali","Jerusalem","Petah Tikva","Berlin"],"job_type":"project","company":"Bcards"},{"title":"Careers advisor","locations":["Tel Aviv","New York","Chiang Mai","London","Bali","Jerusalem","Petah Tikva","Berlin"],"job_type":"freelance","company":"nepaid"},{"title":"Handyman","locations":["Tel Aviv","New York","Chiang Mai","London","Bali","Jerusalem","Petah Tikva","Berlin"],"job_type":"full-time","company":"flebit"},{"title":"Film director","locations":["Tel Aviv","New York","Chiang Mai","London","Bali","Jerusalem","Petah Tikva","Berlin"],"job_type":"full-time","company":"splier"},{"title":"Clairvoyant","locations":["Tel Aviv","New York","Chiang Mai","London","Bali","Jerusalem","Petah Tikva","Berlin"],"job_type":"freelance","company":"nepaid"},{"title":"Handyman","locations":["Tel Aviv","New York","Chiang Mai","London","Bali","Jerusalem","Petah Tikva","Berlin"],"job_type":"project","company":"accell"},{"title":"Careers advisor","locations":["Tel Aviv","New York","Chiang Mai","London","Bali","Jerusalem","Petah Tikva","Berlin"],"job_type":"part-time","company":"Locard"},{"title":"Casual worker","locations":["Tel Aviv","New York","Chiang Mai","London","Bali","Jerusalem","Petah Tikva","Berlin"],"job_type":"freelance","company":"splier"},{"title":"UI Expert","locations":["Tel Aviv","New York","Chiang Mai","London","Bali","Jerusalem","Petah Tikva","Berlin"],"job_type":"project","company":"Trummy"},{"title":"Careers advisor","locations":["Tel Aviv","New York","Chiang Mai","London","Bali","Jerusalem","Petah Tikva","Berlin"],"job_type":"freelance","company":"Spoker"},{"title":"Shark Tamer","locations":["Tel Aviv","New York","Chiang Mai","London","Bali","Jerusalem","Petah Tikva","Berlin"],"job_type":"freelance","company":"Jokens"},{"title":"Lawyer","locations":["Tel Aviv","New York","Chiang Mai","London","Bali","Jerusalem","Petah Tikva","Berlin"],"job_type":"full-time","company":"flebit"},{"title":"Fullstack Developer","locations":["Tel Aviv","New York","Chiang Mai","London","Bali","Jerusalem","Petah Tikva","Berlin"],"job_type":"part-time","company":"Trummy"},{"title":"Backend Developer","locations":["Tel Aviv","New York","Chiang Mai","London","Bali","Jerusalem","Petah Tikva","Berlin"],"job_type":"freelance","company":"Jokens"},{"title":"Business owner","locations":["Tel Aviv","New York","Chiang Mai","London","Bali","Jerusalem","Petah Tikva","Berlin"],"job_type":"full-time","company":"Dataps"},{"title":"Barista","locations":["Tel Aviv","New York","Chiang Mai","London","Bali","Jerusalem","Petah Tikva","Berlin"],"job_type":"freelance","company":"backzy"},{"title":"Barista","locations":["Tel Aviv","New York","Chiang Mai","London","Bali","Jerusalem","Petah Tikva","Berlin"],"job_type":"part-time","company":"accell"},{"title":"Recepetionist","locations":["Tel Aviv","New York","Chiang Mai","London","Bali","Jerusalem","Petah Tikva","Berlin"],"job_type":"project","company":"flebit"},{"title":"DJ","locations":["Tel Aviv","New York","Chiang Mai","London","Bali","Jerusalem","Petah Tikva","Berlin"],"job_type":"part-time","company":"packzy"},{"title":"Soldier","locations":["Tel Aviv","New York","Chiang Mai","London","Bali","Jerusalem","Petah Tikva","Berlin"],"job_type":"freelance","company":"backzy"},{"title":"Recepetionist","locations":["Tel Aviv","New York","Chiang Mai","London","Bali","Jerusalem","Petah Tikva","Berlin"],"job_type":"part-time","company":"accell"},{"title":"Backend Developer","locations":["Tel Aviv","New York","Chiang Mai","London","Bali","Jerusalem","Petah Tikva","Berlin"],"job_type":"full-time","company":"locket"},{"title":"DJ","locations":["Tel Aviv","New York","Chiang Mai","London","Bali","Jerusalem","Petah Tikva","Berlin"],"job_type":"part-time","company":"Bcards"},{"title":"Careers advisor","locations":["Tel Aviv","New York","Chiang Mai","London","Bali","Jerusalem","Petah Tikva","Berlin"],"job_type":"full-time","company":"nepaid"},{"title":"Project Manager","locations":["Tel Aviv","New York","Chiang Mai","London","Bali","Jerusalem","Petah Tikva","Berlin"],"job_type":"full-time","company":"Locard"},{"title":"Shark Tamer","locations":["Tel Aviv","New York","Chiang Mai","London","Bali","Jerusalem","Petah Tikva","Berlin"],"job_type":"full-time","company":"nepaid"},{"title":"Sculptor","locations":["Tel Aviv","New York","Chiang Mai","London","Bali","Jerusalem","Petah Tikva","Berlin"],"job_type":"full-time","company":"Locard"},{"title":"Lawyer","locations":["Tel Aviv","New York","Chiang Mai","London","Bali","Jerusalem","Petah Tikva","Berlin"],"job_type":"project","company":"Jokens"},{"title":"Careers advisor","locations":["Tel Aviv","New York","Chiang Mai","London","Bali","Jerusalem","Petah Tikva","Berlin"],"job_type":"full-time","company":"nvideo"},{"title":"Project Manager","locations":["Tel Aviv","New York","Chiang Mai","London","Bali","Jerusalem","Petah Tikva","Berlin"],"job_type":"freelance","company":"Locard"},{"title":"Project Manager","locations":["Tel Aviv","New York","Chiang Mai","London","Bali","Jerusalem","Petah Tikva","Berlin"],"job_type":"part-time","company":"Spoker"},{"title":"Recepetionist","locations":["Tel Aviv","New York","Chiang Mai","London","Bali","Jerusalem","Petah Tikva","Berlin"],"job_type":"freelance","company":"backzy"},{"title":"Fullstack Developer","locations":["Tel Aviv","New York","Chiang Mai","London","Bali","Jerusalem","Petah Tikva","Berlin"],"job_type":"project","company":"nepaid"},{"title":"Film director","locations":["Tel Aviv","New York","Chiang Mai","London","Bali","Jerusalem","Petah Tikva","Berlin"],"job_type":"freelance","company":"backzy"},{"title":"Backend Developer","locations":["Tel Aviv","New York","Chiang Mai","London","Bali","Jerusalem","Petah Tikva","Berlin"],"job_type":"part-time","company":"yeswap"},{"title":"DJ","locations":["Tel Aviv","New York","Chiang Mai","London","Bali","Jerusalem","Petah Tikva","Berlin"],"job_type":"part-time","company":"Trummy"},{"title":"DJ","locations":["Tel Aviv","New York","Chiang Mai","London","Bali","Jerusalem","Petah Tikva","Berlin"],"job_type":"freelance","company":"nepaid"},{"title":"Product Manager","locations":["Tel Aviv","New York","Chiang Mai","London","Bali","Jerusalem","Petah Tikva","Berlin"],"job_type":"freelance","company":"Eztalk"},{"title":"Backend Developer","locations":["Tel Aviv","New York","Chiang Mai","London","Bali","Jerusalem","Petah Tikva","Berlin"],"job_type":"project","company":"packzy"},{"title":"Clairvoyant","locations":["Tel Aviv","New York","Chiang Mai","London","Bali","Jerusalem","Petah Tikva","Berlin"],"job_type":"project","company":"nepaid"},{"title":"Frontend Developer","locations":["Tel Aviv","New York","Chiang Mai","London","Bali","Jerusalem","Petah Tikva","Berlin"],"job_type":"full-time","company":"backzy"},{"title":"Lawyer","locations":["Tel Aviv","New York","Chiang Mai","London","Bali","Jerusalem","Petah Tikva","Berlin"],"job_type":"freelance","company":"flebit"},{"title":"Cartoonist","locations":["Tel Aviv","New York","Chiang Mai","London","Bali","Jerusalem","Petah Tikva","Berlin"],"job_type":"full-time","company":"packzy"},{"title":"Electrician","locations":["Tel Aviv","New York","Chiang Mai","London","Bali","Jerusalem","Petah Tikva","Berlin"],"job_type":"freelance","company":"nepaid"},{"title":"Product Manager","locations":["Tel Aviv","New York","Chiang Mai","London","Bali","Jerusalem","Petah Tikva","Berlin"],"job_type":"full-time","company":"flebit"},{"title":"Leaflet distributor","locations":["Tel Aviv","New York","Chiang Mai","London","Bali","Jerusalem","Petah Tikva","Berlin"],"job_type":"part-time","company":"flebit"},{"title":"Bodyguard","locations":["Tel Aviv","New York","Chiang Mai","London","Bali","Jerusalem","Petah Tikva","Berlin"],"job_type":"project","company":"flebit"},{"title":"Fullstack Developer","locations":["Tel Aviv","New York","Chiang Mai","London","Bali","Jerusalem","Petah Tikva","Berlin"],"job_type":"full-time","company":"packzy"},{"title":"Electrician","locations":["Tel Aviv","New York","Chiang Mai","London","Bali","Jerusalem","Petah Tikva","Berlin"],"job_type":"project","company":"locket"},{"title":"Electrician","locations":["Tel Aviv","New York","Chiang Mai","London","Bali","Jerusalem","Petah Tikva","Berlin"],"job_type":"project","company":"Jokens"},{"title":"Product Manager","locations":["Tel Aviv","New York","Chiang Mai","London","Bali","Jerusalem","Petah Tikva","Berlin"],"job_type":"freelance","company":"Spoker"},{"title":"Cartoonist","locations":["Tel Aviv","New York","Chiang Mai","London","Bali","Jerusalem","Petah Tikva","Berlin"],"job_type":"project","company":"Locard"},{"title":"Business owner","locations":["Tel Aviv","New York","Chiang Mai","London","Bali","Jerusalem","Petah Tikva","Berlin"],"job_type":"freelance","company":"yeswap"},{"title":"UI Expert","locations":["Tel Aviv","New York","Chiang Mai","London","Bali","Jerusalem","Petah Tikva","Berlin"],"job_type":"project","company":"Trummy"},{"title":"Casual worker","locations":["Tel Aviv","New York","Chiang Mai","London","Bali","Jerusalem","Petah Tikva","Berlin"],"job_type":"part-time","company":"Trummy"},{"title":"Magician","locations":["Tel Aviv","New York","Chiang Mai","London","Bali","Jerusalem","Petah Tikva","Berlin"],"job_type":"part-time","company":"accell"},{"title":"Barista","locations":["Tel Aviv","New York","Chiang Mai","London","Bali","Jerusalem","Petah Tikva","Berlin"],"job_type":"part-time","company":"packzy"},{"title":"Lifeguard","locations":["Tel Aviv","New York","Chiang Mai","London","Bali","Jerusalem","Petah Tikva","Berlin"],"job_type":"project","company":"Trummy"},{"title":"DJ","locations":["Tel Aviv","New York","Chiang Mai","London","Bali","Jerusalem","Petah Tikva","Berlin"],"job_type":"project","company":"Bcards"},{"title":"Clairvoyant","locations":["Tel Aviv","New York","Chiang Mai","London","Bali","Jerusalem","Petah Tikva","Berlin"],"job_type":"part-time","company":"Jokens"},{"title":"Soldier","locations":["Tel Aviv","New York","Chiang Mai","London","Bali","Jerusalem","Petah Tikva","Berlin"],"job_type":"part-time","company":"Bcards"},{"title":"Careers advisor","locations":["Tel Aviv","New York","Chiang Mai","London","Bali","Jerusalem","Petah Tikva","Berlin"],"job_type":"full-time","company":"Bcards"},{"title":"Cabinet maker","locations":["Tel Aviv","New York","Chiang Mai","London","Bali","Jerusalem","Petah Tikva","Berlin"],"job_type":"full-time","company":"flebit"}]